df_import_export/__init__.py
df_import_export/apps.py
df_import_export/import_export.py
df_import_export/models.py
df_import_export/settings.py
django_df_import_export-0.0.2.dist-info/LICENSE
django_df_import_export-0.0.2.dist-info/METADATA
django_df_import_export-0.0.2.dist-info/WHEEL
django_df_import_export-0.0.2.dist-info/top_level.txt
django_df_import_export-0.0.2.dist-info/RECORD
