Metadata-Version: 2.1
Name: django-df-import-export
Version: 0.0.2
Summary: django-df-import-export
Author-email: Apexive OSS <open-source@apexive.com>
License: MIT License
Project-URL: homepage, https://apexive.com/
Classifier: Environment :: Web Environment
Classifier: Framework :: Django
Classifier: Framework :: Django :: 3.2
Classifier: Framework :: Django :: 4.0
Classifier: Intended Audience :: Developers
Classifier: License :: OSI Approved :: MIT License
Classifier: Operating System :: OS Independent
Classifier: Programming Language :: Python
Classifier: Programming Language :: Python :: 3
Classifier: Programming Language :: Python :: 3 :: Only
Classifier: Programming Language :: Python :: 3.9
Classifier: Topic :: Internet
Requires-Python: >=3.9
License-File: LICENSE
Requires-Dist: django
Requires-Dist: django-rest-framework
Requires-Dist: django-import-export
Requires-Dist: tablib
Requires-Dist: requests
Provides-Extra: test
Requires-Dist: pytest ; extra == 'test'
Requires-Dist: pytest-django ; extra == 'test'
Requires-Dist: django-stubs ; extra == 'test'
Requires-Dist: mypy ==1.5.0 ; extra == 'test'
Requires-Dist: black ==23.7.0 ; extra == 'test'
Requires-Dist: ruff ==0.0.284 ; extra == 'test'
Requires-Dist: types-requests ; extra == 'test'
